workflows/__init__.py
workflows/bases.py
workflows/cli.py
workflows/dags.py
workflows/executor.py
workflows/hooks.py
workflows/managers.py
workflows/models.py
workflows/outputs.py
workflows/scheduler.py
workflows/settings.py
workflows/tasks.py
workflows/testing.py
workflows/utilities.py
workflows/version.py
workflows/migrations/0001_initial.py
workflows/migrations/0002_auto_20210702_1959.py
workflows/migrations/__init__.py
workflows/tests/__init__.py
workflows/tests/test_bases.py
workflows/tests/test_cli.py
workflows/tests/test_dags.py
workflows/tests/test_executor.py
workflows/tests/test_hooks.py
workflows/tests/test_manager_kube.py
workflows/tests/test_managers.py
workflows/tests/test_outputs.py
workflows/tests/test_scheduler.py
workflows/tests/test_tasks.py
workflows/tests/test_testing.py
workflows/tests/test_utilities.py
dag_workflows-1.0.5.dist-info/LICENSE
dag_workflows-1.0.5.dist-info/METADATA
dag_workflows-1.0.5.dist-info/WHEEL
dag_workflows-1.0.5.dist-info/entry_points.txt
dag_workflows-1.0.5.dist-info/top_level.txt
dag_workflows-1.0.5.dist-info/RECORD
